flow_core/__init__.py
flow_core/tools/__init__.py
flow_core/tools/create.py
flow_core/tools/delete.py
flow_core/tools/file_utils_create.py
flow_core/tools/login_tool.py
flow_core/tools/read.py
flow_core/tools/utils.py
flow_core/yamls/file_utils_create.yaml
flow_core/yamls/login_tool.yaml
tests/__init__.py
tests/test_login_tool.py
flow_core-0.0.1.dist-info/METADATA
flow_core-0.0.1.dist-info/WHEEL
flow_core-0.0.1.dist-info/entry_points.txt
flow_core-0.0.1.dist-info/top_level.txt
flow_core-0.0.1.dist-info/RECORD
