Metadata-Version: 2.1
Name: flow-core
Version: 0.0.1
Summary: This is my tools package
